README.md
setup.py
ngs_utils/Sample.py
ngs_utils/__init__.py
ngs_utils/_version.py
ngs_utils/bam_utils.py
ngs_utils/bcbio.py
ngs_utils/bed_utils.py
ngs_utils/call_process.py
ngs_utils/chrom_utils.py
ngs_utils/config.py
ngs_utils/file_utils.py
ngs_utils/gtf.py
ngs_utils/key_genes_utils.py
ngs_utils/logger.py
ngs_utils/parallel.py
ngs_utils/proc_args.py
ngs_utils/sambamba.py
ngs_utils/setup_utils.py
ngs_utils/sex.py
ngs_utils/testing.py
ngs_utils/utils.py
ngs_utils/variant_filtering.py
ngs_utils/vcf_utils.py
ngs_utils.egg-info/PKG-INFO
ngs_utils.egg-info/SOURCES.txt
ngs_utils.egg-info/dependency_links.txt
ngs_utils.egg-info/entry_points.txt
ngs_utils.egg-info/not-zip-safe
ngs_utils.egg-info/requires.txt
ngs_utils.egg-info/top_level.txt
scripts/bed_file_from_gene_list.py
scripts/cols
scripts/group_and_merge_by_gene.py
scripts/hg19_addchr.py
scripts/html_to_base64.py
scripts/qstat.py
scripts/sort_bed.py
scripts/split_bed.py
scripts/standardize_bed.py
scripts/tabutils
scripts/tsv
tab_utils/__init__.py
tab_utils/support.py
tab_utils/tab_filter.py
tab_utils/tab_merge.py
tab_utils/tab_reorder.py
tab_utils/tab_tag.py
tab_utils/tab_view.py