Metadata-Version: 1.1
Name: ngs-utils
Version: 2.3.16
Summary: Utils for NGS pipelines by Vlad Saveliev
Home-page: https://github.com/vladsaveliev/NGS_Utils
Author: Vlad Saveliev
Author-email: vlad.saveliev@astrazeneca.com
License: GPLv3
Keywords: bioinformatics
Platform: UNKNOWN
Classifier: Environment :: Console
Classifier: Environment :: Web Environment
Classifier: Intended Audience :: Science/Research
Classifier: License :: OSI Approved :: GNU General Public License v3 (GPLv3)
Classifier: Natural Language :: English
Classifier: Operating System :: MacOS :: MacOS X
Classifier: Operating System :: POSIX
Classifier: Operating System :: Unix
Classifier: Programming Language :: Python
Classifier: Programming Language :: JavaScript
Classifier: Topic :: Scientific/Engineering
Classifier: Topic :: Scientific/Engineering :: Bio-Informatics
